emp_wsb/__init__.py
emp_wsb/__main__.py
emp_wsb/cli.py
emp_wsb/logo.py
emp_wsb/rawrepl.py
emp_wsb/wsb.py
emp_wsb/wserver.py
emp_wsb-0.1.2.dist-info/AUTHORS
emp_wsb-0.1.2.dist-info/LICENSE
emp_wsb-0.1.2.dist-info/METADATA
emp_wsb-0.1.2.dist-info/WHEEL
emp_wsb-0.1.2.dist-info/entry_points.txt
emp_wsb-0.1.2.dist-info/pbr.json
emp_wsb-0.1.2.dist-info/top_level.txt
emp_wsb-0.1.2.dist-info/RECORD
