Metadata-Version: 2.1
Name: emp-wsb
Version: 0.1.2
Summary: EMP-IDE Websocket-Serialport-Bridge
Home-page: https://github.com/EasyMicroPython/EMP-WSB
Author: singein
Author-email: singein@outlook.com
License: MIT
Platform: UNKNOWN
Requires-Dist: fire
Requires-Dist: pyserial
Requires-Dist: wheel
